README.md
setup.py
damip_robots/__init__.py
damip_robots/asrredis.py
damip_robots/config.py
damip_robots/glmcloud.py
damip_robots/pvoice.py
damip_robots/rayranger.py
damip_robots.egg-info/PKG-INFO
damip_robots.egg-info/SOURCES.txt
damip_robots.egg-info/dependency_links.txt
damip_robots.egg-info/requires.txt
damip_robots.egg-info/top_level.txt