Metadata-Version: 2.1
Name: damip-robots
Version: 0.1.9
Summary: Robots SDK for Digitopia Advanced Mechanical Intelligence Platform.
Home-page: https://digitopia.com.cn/damip-robots
Author: kaiwei.li
Author-email: kaiwei.li@digitopia.com.cn
License: UNKNOWN
Platform: UNKNOWN
Classifier: Development Status :: 3 - Alpha
Classifier: Intended Audience :: Developers
Classifier: Topic :: Software Development :: Build Tools
Classifier: License :: OSI Approved :: MIT License
Classifier: Programming Language :: Python :: 3
Classifier: Programming Language :: Python :: 3.6
Classifier: Programming Language :: Python :: 3.7
Classifier: Programming Language :: Python :: 3.8
Classifier: Programming Language :: Python :: 3.9
Requires-Python: >=3.6
